spiderosm
