Metadata-Version: 1.1
Name: spiderosm
Version: 0.4.3
Summary: GIS conflation tool for matching street networks.
Home-page: http://spiderosm.org
Author: Michael Arnold
Author-email: mha@spiderosm.org
License: MIT
Keywords: GIS conflation OSM OpenStreetMaps centerline jurisdictional street network matcher
Platform: UNKNOWN
Classifier: Development Status :: 4 - Beta
Classifier: License :: OSI Approved :: MIT License
Classifier: Programming Language :: Python :: 2.7
Classifier: Topic :: Scientific/Engineering :: GIS
